core/__init__.py
core/molecule.py
core/orbital_calculation.py
core/reaction_mechanism.py
io/__init__.py
io/data_exporters.py
io/file_parsers.py
tests/__init__.py
tests/test_molecule.py
tests/test_orbital_calculation.py
utils/__init__.py
utils/math_utils.py
visualization/__init__.py
visualization/orbital_visualization.py
molecular_orbitals-0.1.0.dist-info/LICENSE
molecular_orbitals-0.1.0.dist-info/METADATA
molecular_orbitals-0.1.0.dist-info/WHEEL
molecular_orbitals-0.1.0.dist-info/entry_points.txt
molecular_orbitals-0.1.0.dist-info/top_level.txt
molecular_orbitals-0.1.0.dist-info/RECORD
